eventuali-0.1.1.dist-info/METADATA
eventuali-0.1.1.dist-info/WHEEL
eventuali-0.1.1.dist-info/entry_points.txt
eventuali-0.1.1.dist-info/licenses/LICENSE-APACHE
eventuali-0.1.1.dist-info/licenses/LICENSE-MIT
eventuali/__init__.py
eventuali/_eventuali.pyd
eventuali/aggregate.py
eventuali/cli.py
eventuali/event.py
eventuali/event_store.py
eventuali/exceptions.py
eventuali/performance/__init__.py
eventuali/snapshot.py
eventuali/streaming.py
eventuali-0.1.1.dist-info/RECORD
