Metadata-Version: 2.4
Name: eventuali
Version: 0.1.1
Classifier: Development Status :: 3 - Alpha
Classifier: Intended Audience :: Developers
Classifier: License :: OSI Approved :: MIT License
Classifier: License :: OSI Approved :: Apache Software License
Classifier: Programming Language :: Python :: 3
Classifier: Programming Language :: Python :: 3.8
Classifier: Programming Language :: Python :: 3.9
Classifier: Programming Language :: Python :: 3.10
Classifier: Programming Language :: Python :: 3.11
Classifier: Programming Language :: Python :: 3.12
Classifier: Programming Language :: Rust
Classifier: Topic :: Database
Classifier: Topic :: Software Development :: Libraries :: Python Modules
Requires-Dist: pydantic>=2.0.0
Requires-Dist: pytest>=8.3.5
Requires-Dist: pytest-asyncio>=0.24.0
Requires-Dist: typing-extensions>=4.0.0
Requires-Dist: click>=8.0.0
Requires-Dist: rich>=13.0.0
Requires-Dist: tabulate>=0.9.0
Requires-Dist: requests>=2.32.4
Requires-Dist: pyyaml>=6.0.2
Requires-Dist: psutil>=7.0.0
Requires-Dist: asyncio>=4.0.0
Requires-Dist: maturin>=1.9.3
Requires-Dist: pytest>=7.0.0 ; extra == 'dev'
Requires-Dist: pytest-asyncio>=0.21.0 ; extra == 'dev'
Requires-Dist: black>=23.0.0 ; extra == 'dev'
Requires-Dist: isort>=5.12.0 ; extra == 'dev'
Requires-Dist: mypy>=1.0.0 ; extra == 'dev'
Requires-Dist: ruff>=0.1.0 ; extra == 'dev'
Provides-Extra: dev
License-File: LICENSE-APACHE
License-File: LICENSE-MIT
Summary: High-performance event sourcing library combining Rust performance with Python ease of use
Keywords: event-sourcing,cqrs,rust,python,performance
Author-email: PrimevalAI <info@primeval.ai>
License: MIT OR Apache-2.0
Requires-Python: >=3.8
Project-URL: Homepage, https://github.com/primevalai/onyx-octopus
Project-URL: Repository, https://github.com/primevalai/onyx-octopus
Project-URL: Documentation, https://github.com/primevalai/onyx-octopus
Project-URL: Issues, https://github.com/primevalai/onyx-octopus/issues
Project-URL: Changelog, https://github.com/primevalai/onyx-octopus/releases
